Metadata-Version: 2.1
Name: qforce
Version: 0.6.14
Summary: Q-Force: Quantum mechanically augmented molecular force fields
Home-page: https://github.com/selimsami/qforce
Author: Selim Sami
Author-email: s.sami@rug.nl
Keywords: qm forcefield md
Classifier: Development Status :: 4 - Beta
Classifier: Environment :: Console
Classifier: Intended Audience :: Science/Research
Classifier: License :: OSI Approved :: Apache Software License
Classifier: Programming Language :: Python :: 3.7
Classifier: Programming Language :: Python :: 3.8
Classifier: Programming Language :: Python :: 3.9
Classifier: Topic :: Scientific/Engineering :: Chemistry
License-File: LICENCE
